rythmnet/__init__.py
rythmnet/src/__init__.py
rythmnet/src/config.py
rythmnet/src/engine.py
rythmnet/src/engine_vipl.py
rythmnet/src/main.py
rythmnet/src/loss_func/__init__.py
rythmnet/src/loss_func/custom_loss.py
rythmnet/src/loss_func/rhythmnet_loss.py
rythmnet/src/models/__init__.py
rythmnet/src/models/lenet.py
rythmnet/src/models/resnet.py
rythmnet/src/models/rhythmNet.py
rythmnet/src/models/simpleCNN.py
rythmnet/src/utils/__init__.py
rythmnet/src/utils/dataset.py
rythmnet/src/utils/generate_fold_csv.py
rythmnet/src/utils/model_utils.py
rythmnet/src/utils/plot_scripts.py
rythmnet/src/utils/signal_utils.py
rythmnet/src/utils/video2st_maps.py
rythmnet/utils/__init__.py
rythmnet/utils/config.py
rythmnet/utils/datagenerator.py
rythmnet/utils/engine_vipl.py
rythmnet/utils/model_utils.py
rythmnet/utils/plot_scripts.py
rythmnet/utils/resnet.py
rythmnet/utils/rhythmnet.py
rythmnet/utils/rhythmnet_loss.py
rythmnet-0.0.1.dist-info/METADATA
rythmnet-0.0.1.dist-info/WHEEL
rythmnet-0.0.1.dist-info/top_level.txt
rythmnet-0.0.1.dist-info/RECORD
