Metadata-Version: 2.1
Name: rythmnet
Version: 0.0.1
Summary: Rythmnet_implementation
Author: ErnisMeshi
Author-email: ernis.meshi@student.uni-pr.edu
Classifier: Programming Language :: Python :: 3.10
